ide_rules/__init__.py
ide_rules/main.py
ide_rules-0.1.0.data/data/ide_rules/rules/domain-terminology.mdc
ide_rules-0.1.0.data/data/ide_rules/rules/fastapi-patterns.mdc
ide_rules-0.1.0.data/data/ide_rules/rules/makefile-patterns.mdc
ide_rules-0.1.0.data/data/ide_rules/rules/polars-usage.mdc
ide_rules-0.1.0.data/data/ide_rules/rules/prompt-engineering.mdc
ide_rules-0.1.0.data/data/ide_rules/rules/pytest-testing.mdc
ide_rules-0.1.0.data/data/ide_rules/rules/python-style.mdc
ide_rules-0.1.0.data/data/ide_rules/rules/script-organization.mdc
ide_rules-0.1.0.data/data/ide_rules/rules/typer-cli.mdc
ide_rules-0.1.0.data/data/ide_rules/rules/uv-python-management.mdc
ide_rules-0.1.0.dist-info/METADATA
ide_rules-0.1.0.dist-info/WHEEL
ide_rules-0.1.0.dist-info/entry_points.txt
ide_rules-0.1.0.dist-info/RECORD
