Metadata-Version: 2.4
Name: ide-rules
Version: 0.1.0
Summary: A tool to manage IDE rules files for Windsurf and Cursor
Project-URL: Homepage, https://github.com/yourusername/ide-rules
Project-URL: Repository, https://github.com/yourusername/ide-rules
Project-URL: Issues, https://github.com/yourusername/ide-rules/issues
Author-email: Your Name <you@example.com>
License: MIT
Keywords: cursor,development,ide,rules,windsurf
Classifier: Development Status :: 4 - Beta
Classifier: Intended Audience :: Developers
Classifier: License :: OSI Approved :: MIT License
Classifier: Programming Language :: Python :: 3
Classifier: Programming Language :: Python :: 3.12
Classifier: Topic :: Software Development
Classifier: Topic :: Text Editors
Requires-Python: >=3.12
Requires-Dist: rich>=13.7.0
Requires-Dist: typer>=0.12.0
